machineid/__init__.py
machineid/client.py
machineid_io-0.1.6.dist-info/METADATA
machineid_io-0.1.6.dist-info/WHEEL
machineid_io-0.1.6.dist-info/licenses/LICENSE
machineid_io-0.1.6.dist-info/RECORD
