Metadata-Version: 2.4
Name: machineid-io
Version: 0.1.6
Summary: Official Python SDK for the MachineID.io API
Project-URL: Homepage, https://machineid.io
Project-URL: Repository, https://github.com/machineid-io/python-sdk
Author: MachineID.io
License: MIT
License-File: LICENSE
Requires-Python: >=3.8
Requires-Dist: requests>=2.0.0
